PyExpansion/__init__.py
PyExpansion/version.py
PyExpansion/application/__init__.py
PyExpansion/application/finance/__init__.py
PyExpansion/application/finance/calculator.py
PyExpansion/application/finance/utils.py
PyExpansion/application/human_resource/__init__.py
PyExpansion/application/human_resource/PyIC/__init__.py
PyExpansion/application/human_resource/PyIC/main.py
PyExpansion/application/human_resource/PyIC/status_code_list.py
PyExpansion/application/human_resource/PyIC/tests.py
PyExpansion/application/human_resource/PyIC/country/Malaysia.py
PyExpansion/application/human_resource/PyIC/country/Singapore.py
PyExpansion/application/human_resource/PyIC/country/__init__.py
PyExpansion/application/human_resource/PyIC/country/base.py
PyExpansion/application/maths/__init__.py
PyExpansion/application/maths/general.py
PyExpansion/application/maths/table.py
PyExpansion/application/security/__init__.py
PyExpansion/application/security/password_generator/__init__.py
PyExpansion/application/security/password_generator/main.py
PyExpansion/application/security/password_generator/tests.py
PyExpansion/application/web/__init__.py
PyExpansion/common/__init__.py
PyExpansion/common/basic_function.py
PyExpansion/common/extend.py
PyExpansion/common/message.py
PyExpansion/common/table.py
PyExpansion/common/utils.py
PyExpansion/common/version_history.py
PyExpansion/common/constants/__init__.py
PyExpansion/common/constants/common.py
PyExpansion/common/constants/datetime.py
PyExpansion/common/constants/file_extension.py
PyExpansion/common/data_type/__init__.py
PyExpansion/common/data_type/lists/__init__.py
PyExpansion/common/data_type/lists/main.py
PyExpansion/common/data_type/lists/status_code_list.py
PyExpansion/common/data_type/lists/tests.py
PyExpansion/common/date_time/__init__.py
PyExpansion/common/date_time/reality.py
PyExpansion/common/date_time/utils.py
PyExpansion/common/status_code/__init__.py
PyExpansion/common/status_code/http_code.py
PyExpansion/common/status_code/utils.py
PyExpansion-0.0.1a20240225.dist-info/LICENSE.txt
PyExpansion-0.0.1a20240225.dist-info/METADATA
PyExpansion-0.0.1a20240225.dist-info/WHEEL
PyExpansion-0.0.1a20240225.dist-info/top_level.txt
PyExpansion-0.0.1a20240225.dist-info/RECORD
