Metadata-Version: 2.1
Name: PyExpansion
Version: 0.0.1a20240225
Requires-Python: >=3
License-File: LICENSE.txt
